[
    {
        "id": 1,
        "titulo": "O labirinto do Logcat",
        "capa": "https://caelum-online-public.s3.amazonaws.com/2802-react-praticando/img2.png",
        "link": "https://www.youtube.com/embed/ypvGqZGJBls",
        "descricao": "Mais um #AluraMais para quem é Dev Mobile "
    },
    {
        "id": 2,
        "titulo": "Um componente no espaço",
        "capa": "https://caelum-online-public.s3.amazonaws.com/2802-react-praticando/img1.png",
        "link": "https://www.youtube.com/embed/jK0uiQ1ZQQQ",
        "descricao": "Se você utiliza #React este vídeo é para você."
    },
    {
        "id": 3,
        "titulo": "O poderoso JavaScript",
        "capa": "https://caelum-online-public.s3.amazonaws.com/2802-react-praticando/img4.png",
        "link": "https://www.youtube.com/embed/N1BSG02z-Mw",
        "descricao": "JavaScript é uma das principais linguagens de programação no mercado, sendo eleita em 2021 como a linguagem mais utilizada pelos Brasileiros, de acordo com relatório elaborado pelo GitHub. "
    },
    {
        "id": 4,
        "titulo": "Dart, o Caçador de Andróides",
        "capa": "https://caelum-online-public.s3.amazonaws.com/2802-react-praticando/img3.png",
        "link": "https://www.youtube.com/embed/LLmBWjF6F8M",
        "descricao": "Vem com a gente e com o Ricarth Lima, que é um dos Instrutores da Escola Mobile aqui na Alura, para aprender um pouco mais sobre a linguagem de programação Dart. Vamos nessa? 😜"
    }
]